Workbook

Sheet Raw_Data
A1: CLARO TV+ — DADOS HISTÓRICOS DE PREÇO E ASSINANTES POR PACOTE
A2: Preencha com dados reais. Células azuis = inputs editáveis. | Período: Jan/2023 – Dez/2024 (24 meses)
A3: Mês | B3: Ano | C3: Pacote | D3: Preço_Mensal (R$) | E3: Assinantes_Ativos | F3: Novos_Assinantes | G3: Cancelamentos | H3: Receita_Total (R$) | I3: Promo_Flag (0/1) | J3: Sazonality_Index | K3: Concorrente_Preço_Ref (R$) | L3: Notas
A4: Jan | B4: 2023 | C4: Futebol | D4: 89.9 | E4: 69700 | F4: 5576 | G4: 4182 | H4: 6266030 | I4: 1 | J4: 0.82 | K4: 79.11
A5: Jan | B5: 2023 | C5: MMA/Combate | D5: 64.9 | E5: 34440 | F5: 2755 | G5: 2066 | H5: 2235156 | I5: 1 | J5: 0.82 | K5: 57.11
A6: Jan | B6: 2023 | C6: Familia | D6: 129.9 | E6: 172200 | F6: 13776 | G6: 10332 | H6: 22368780 | I6: 1 | J6: 0.82 | K6: 114.31
A7: Jan | B7: 2023 | C7: Series/Filmes | D7: 49.9 | E7: 55760 | F7: 4460 | G7: 3345 | H7: 2782424 | I7: 1 | J7: 0.82 | K7: 43.91
A8: Jan | B8: 2023 | C8: Infantil | D8: 39.9 | E8: 45100 | F8: 3608 | G8: 2706 | H8: 1799490 | I8: 1 | J8: 0.82 | K8: 35.11
A9: Jan | B9: 2023 | C9: Bundle_Plus | D9: 179.9 | E9: 77900 | F9: 6232 | G9: 4674 | H9: 14014210 | I9: 1 | J9: 0.82 | K9: 158.31
A10: Fev | B10: 2023 | C10: Futebol | D10: 89.9 | E10: 66300 | F10: 5304 | G10: 3978 | H10: 5960370 | I10: 0 | J10: 0.78 | K10: 79.11
A11: Fev | B11: 2023 | C11: MMA/Combate | D11: 64.9 | E11: 32760 | F11: 2620 | G11: 1965 | H11: 2126124 | I11: 0 | J11: 0.78 | K11: 57.11
A12: Fev | B12: 2023 | C12: Familia | D12: 129.9 | E12: 163800 | F12: 13104 | G12: 9828 | H12: 21277620 | I12: 0 | J12: 0.78 | K12: 114.31
A13: Fev | B13: 2023 | C13: Series/Filmes | D13: 49.9 | E13: 53040 | F13: 4243 | G13: 3182 | H13: 2646696 | I13: 0 | J13: 0.78 | K13: 43.91
A14: Fev | B14: 2023 | C14: Infantil | D14: 39.9 | E14: 42900 | F14: 3432 | G14: 2574 | H14: 1711710 | I14: 0 | J14: 0.78 | K14: 35.11
A15: Fev | B15: 2023 | C15: Bundle_Plus | D15: 179.9 | E15: 74100 | F15: 5928 | G15: 4446 | H15: 13330590 | I15: 0 | J15: 0.78 | K15: 158.31
... A147: Dez | B147: 2024 | C147: Bundle_Plus | D147: 194.29 | E147: 121125 | F147: 9690 | G147: 7267 | H147: 23533376 | I147: 1 | J147: 1.25 | K147: 170.98
A149: LEGENDA:
A150: Células em azul claro = inputs editáveis pelo usuário

Sheet Elasticity_Model
A1: MODELO DE ELASTICIDADE DE PREÇO — REGRESSÃO LOG-LOG POR PACOTE
A2: Equação: ln(Demanda) = α + β × ln(Preço) + γ × Sazonalidade + δ × Promo_Flag | β = Elasticidade-Preço | Células amarelas = assunções chave
A4: 1. FUNDAMENTO MATEMÁTICO — REGRESSÃO LOG-LOG
A5: Forma funcional: | B5: ln(Q) = α + β·ln(P) + γ·S + δ·D + ε
A6: Onde: | B6: Q = Assinantes Ativos | P = Preço Mensal | S = Índice de Sazonalidade | D = Dummy de Promoção
A7: Interpretação β: | B7: β = Elasticidade-preço. Se β = -0.8, um aumento de 10% no preço reduz demanda em 8%
A8: Estimação: | B8: OLS (Mínimos Quadrados Ordinários) aplicado em logaritmos naturais dos dados históricos
A10: 2. RESULTADOS DE ELASTICIDADE POR PACOTE (Preencha com dados reais ou use estimativas abaixo)
A11: Pacote | B11: Preço Atual (R$) | C11: Assinantes Atuais | D11: Elasticidade β (estimada) | E11: Erro Padrão β | F11: t-stat | G11: p-valor | H11: R² Modelo | I11: Classificação Elasticidade | J11: WTP Mín (R$) | K11: WTP Máx (R$) | L11: Preço Ótimo (R$) | M11: Receita Atual (R$mm) | N11: Receita Ótima (R$mm)
A12: Futebol | B12: 89.9 | C12: 95000 | D12: -0.45 | E12: 0.08 | F12: -5.63 | G12: 0.001 | H12: 0.87 | I12: Inelástico | J12: 70 | K12: 130 | L12: =K12*0.75 -> 97.5 | M12: =B12*C12/1000000 -> 8.5405 | N12: =L12*C12*(L12/B12)^D12/1000000 -> 8.9303402
A13: MMA/Combate | B13: 64.9 | C13: 42000 | D13: -0.62 | E13: 0.11 | F13: -5.64 | G13: 0.001 | H13: 0.81 | I13: Inelástico | J13: 50 | K13: 95 | L13: =K13*0.75 -> 71.25 | M13: =B13*C13/1000000 -> 2.7258 | N13: =L13*C13*(L13/B13)^D13/1000000 -> 2.8242247
A14: Familia | B14: 129.9 | C14: 210000 | D14: -0.78 | E14: 0.09 | F14: -8.67 | G14: 0 | H14: 0.92 | I14: Inelástico | J14: 90 | K14: 170 | L14: =K14*0.75 -> 127.5 | M14: =B14*C14/1000000 -> 27.279 | N14: =L14*C14*(L14/B14)^D14/1000000 -> 27.167312
A15: Series/Filmes | B15: 49.9 | C15: 68000 | D15: -1.35 | E15: 0.14 | F15: -9.64 | G15: 0 | H15: 0.89 | I15: Elástico | J15: 35 | K15: 80 | L15: =K15*0.75 -> 60 | M15: =B15*C15/1000000 -> 3.3932 | N15: =L15*C15*(L15/B15)^D15/1000000 -> 3.1812054
A16: Infantil | B16: 39.9 | C16: 55000 | D16: -0.85 | E16: 0.12 | F16: -7.08 | G16: 0 | H16: 0.84 | I16: Inelástico | J16: 30 | K16: 65 | L16: =K16*0.75 -> 48.75 | M16: =B16*C16/1000000 -> 2.1945 | N16: =L16*C16*(L16/B16)^D16/1000000 -> 2.261444
A17: Bundle_Plus | B17: 179.9 | C17: 95000 | D17: -0.55 | E17: 0.1 | F17: -5.5 | G17: 0.001 | H17: 0.88 | I17: Inelástico | J17: 140 | K17: 230 | L17: =K17*0.75 -> 172.5 | M17: =B17*C17/1000000 -> 17.0905 | N17: =L17*C17*(L17/B17)^D17/1000000 -> 16.770493
A18: TOTAL PORTFÓLIO | M18: =SUM(M12:M17) -> 61.2235 | N18: =SUM(N12:N17) -> 61.13502
A20: 3. GUIA DE INTERPRETAÇÃO DA ELASTICIDADE
A21: Range β | B21: Classificação | C21: Interpretação para CMO
A22: β < -1.0 | B22: ELÁSTICO | C22: Demanda sensível a preço. Aumentar preço reduz receita. Foco em volume.
A23: β entre -1.0 e -0.5 | B23: INELÁSTICO MODERADO | C23: Espaço para aumentar preço com perda moderada de assinantes.
A24: β entre -0.5 e 0.0 | B24: INELÁSTICO FORTE | C24: Alta fidelidade. Aumentar preço aumenta receita. Conteúdo exclusivo âncora.

Sheet WTP_Conjoint
A1: ANÁLISE DE WILLINGNESS-TO-PAY — VAN WESTENDORP PRICE SENSITIVITY METER
A2: Metodologia: 4 perguntas sobre percepção de preço aplicadas por segmento. O cruzamento das curvas define Acceptable Price Range e Optimal Price Point.
A4: 1. AS 4 PERGUNTAS DO VAN WESTENDORP (aplicar em survey por segmento)
A5: Q1 — Caro demais: | D5: A que preço este pacote seria TÃO CARO que você não o compraria?
A6: Q2 — Caro mas aceitável: | D6: A que preço este pacote seria CARO, mas você ainda consideraria comprar?
A7: Q3 — Bom negócio: | D7: A que preço este pacote seria um BOM NEGÓCIO?
A8: Q4 — Barato demais: | D8: A que preço este pacote seria TÃO BARATO que você duvidaria da qualidade?
A10: 2. RESULTADOS WTP POR SEGMENTO — INSIRA OS PERCENTIS DA SUA SURVEY
A11: Segmento / Pacote | B11: n Survey | C11: Q1 p50 Caro demais | D11: Q2 p50 Caro aceitável | E11: Q3 p50 Bom negócio | F11: Q4 p50 Barato demais | G11: Preço Mínimo Aceitável (PMC) | H11: Preço Máximo Aceitável (PME) | I11: Faixa Aceitável (R$) | J11: Optimal Price Point | K11: Preço Atual (R$) | L11: Delta OPP vs Atual | M11: Ação Recomendada
A12: Futebol | B12: 450 | C12: 140 | D12: 110 | E12: 75 | F12: 45 | G12: =F12 -> 45 | H12: =D12 -> 110 | I12: =H12-G12 -> 65 | J12: =(D12+E12)/2 -> 92.5 | K12: 89.9 | L12: =J12-K12 -> 2.6 | M12: =_xlfn.IFS(L12>20,"↑ Aumentar preço",L12<-20,"↓ Reduzir preço",TRUE(),"= Manter preço") -> = Manter preço
A13: MMA/Combate | B13: 280 | C13: 95 | D13: 80 | E13: 55 | F13: 35 | G13: =F13 -> 35 | H13: =D13 -> 80 | I13: =H13-G13 -> 45 | J13: =(D13+E13)/2 -> 67.5 | K13: 64.9 | L13: =J13-K13 -> 2.6 | M13: =_xlfn.IFS(L13>20,"↑ Aumentar preço",L13<-20,"↓ Reduzir preço",TRUE(),"= Manter preço") -> = Manter preço
A14: Familia | B14: 620 | C14: 190 | D14: 150 | E14: 95 | F14: 60 | G14: =F14 -> 60 | H14: =D14 -> 150 | I14: =H14-G14 -> 90 | J14: =(D14+E14)/2 -> 122.5 | K14: 129.9 | L14: =J14-K14 -> -7.4 | M14: =_xlfn.IFS(L14>20,"↑ Aumentar preço",L14<-20,"↓ Reduzir preço",TRUE(),"= Manter preço") -> = Manter preço
A15: Series/Filmes | B15: 380 | C15: 85 | D15: 65 | E15: 42 | F15: 25 | G15: =F15 -> 25 | H15: =D15 -> 65 | I15: =H15-G15 -> 40 | J15: =(D15+E15)/2 -> 53.5 | K15: 49.9 | L15: =J15-K15 -> 3.6 | M15: =_xlfn.IFS(L15>20,"↑ Aumentar preço",L15<-20,"↓ Reduzir preço",TRUE(),"= Manter preço") -> = Manter preço
A16: Infantil | B16: 290 | C16: 70 | D16: 55 | E16: 35 | F16: 20 | G16: =F16 -> 20 | H16: =D16 -> 55 | I16: =H16-G16 -> 35 | J16: =(D16+E16)/2 -> 45 | K16: 39.9 | L16: =J16-K16 -> 5.1 | M16: =_xlfn.IFS(L16>20,"↑ Aumentar preço",L16<-20,"↓ Reduzir preço",TRUE(),"= Manter preço") -> = Manter preço
A17: Bundle_Plus | B17: 510 | C17: 260 | D17: 200 | E17: 140 | F17: 90 | G17: =F17 -> 90 | H17: =D17 -> 200 | I17: =H17-G17 -> 110 | J17: =(D17+E17)/2 -> 170 | K17: 179.9 | L17: =J17-K17 -> -9.9 | M17: =_xlfn.IFS(L17>20,"↑ Aumentar preço",L17<-20,"↓ Reduzir preço",TRUE(),"= Manter preço") -> = Manter preço

Sheet Bundle_Optimizer
A1: OTIMIZADOR DE BUNDLES — DESIGN E PRECIFICAÇÃO DE PACOTES COMBINADOS
A2: Princípio: Bundling captura heterogeneidade de WTP entre segmentos. Objetivo: Maximizar receita total escolhendo preço e composição de cada bundle.
A4: 1. MATRIZ DE COMPOSIÇÃO DOS BUNDLES — O QUE CADA TIER INCLUI
A5: Bundle / Tier | B5: Futebol | C5: MMA/ Combate | D5: Familia | E5: Series/ Filmes | F5: Infantil | G5: Streamings (Netflix etc) | H5: Nº Telas | I5: HD/4K | J5: Preço Sugerido (R$) | K5: Preço Atual (R$)
A6: Essencial | B6: ✗ | C6: ✗ | D6: ✗ | E6: ✓ | F6: ✓ | G6: ✗ | H6: 1 | I6: HD | J6: 49.9 | K6: 49.9
A7: Plus | B7: ✓ | C7: ✗ | D7: ✓ | E7: ✓ | F7: ✓ | G7: ✗ | H7: 2 | I7: HD | J7: 99.9 | K7: 99.9
A8: Premium | B8: ✓ | C8: ✓ | D8: ✓ | E8: ✓ | F8: ✓ | G8: ✓ | H8: 4 | I8: 4K | J8: 179.9 | K8: 179.9
A9: Familia Plus | B9: ✗ | C9: ✗ | D9: ✓ | E9: ✓ | F9: ✓ | G9: ✗ | H9: 3 | I9: HD | J9: 84.9 | K9: 84.9
A10: Esporte Total | B10: ✓ | C10: ✓ | D10: ✗ | E10: ✗ | F10: ✗ | G10: ✗ | H10: 2 | I10: HD | J10: 89.9 | K10: 89.9
A11: Futebol Add | B11: ✓ | C11: ✗ | D11: ✗ | E11: ✗ | F11: ✗ | G11: ✗ | H11: 1 | I11: HD | J11: 39.9 | K11: 39.9
A14: 2. SIMULAÇÃO DE RECEITA POR BUNDLE — CENÁRIOS DE PREÇO
A15: Bundle | B15: Preço Base (R$) | C15: Elast. Média Ponderada | D15: Assin. Base | E15: Preço Cenário -15% | F15: Assin. -15% | G15: Receita -15% (R$mm) | H15: Preço Cenário Atual | I15: Receita Atual (R$mm) | J15: Preço Cenário +15% | K15: Assin. +15%
A16: Essencial | B16: 49.9 | C16: -1.35 | D16: 68000 | E16: =B16*0.85 -> 42.415 | F16: =D16*(0.85^C16) -> 84682.44 | G16: =E16*F16/1000000 -> 3.5918057 | H16: =B16 -> 49.9 | I16: =B16*D16/1000000 -> 3.3932 | J16: =B16*1.15 -> 57.385 | K16: =D16*(1.15^C16) -> 56307.576
A17: Plus | B17: 99.9 | C17: -0.65 | D17: 180000 | E17: =B17*0.85 -> 84.915 | F17: =D17*(0.85^C17) -> 200055.37 | G17: =E17*F17/1000000 -> 16.987701 | H17: =B17 -> 99.9 | I17: =B17*D17/1000000 -> 17.982 | J17: =B17*1.15 -> 114.885 | K17: =D17*(1.15^C17) -> 164368.62
A18: Premium | B18: 179.9 | C18: -0.55 | D18: 95000 | E18: =B18*0.85 -> 152.915 | F18: =D18*(0.85^C18) -> 103882.69 | G18: =E18*F18/1000000 -> 15.885222 | H18: =B18 -> 179.9 | I18: =B18*D18/1000000 -> 17.0905 | J18: =B18*1.15 -> 206.885 | K18: =D18*(1.15^C18) -> 87971.054
A19: Familia Plus | B19: 84.9 | C19: -0.8 | D19: 120000 | E19: =B19*0.85 -> 72.165 | F19: =D19*(0.85^C19) -> 136661.48 | G19: =E19*F19/1000000 -> 9.8621754 | H19: =B19 -> 84.9 | I19: =B19*D19/1000000 -> 10.188 | J19: =B19*1.15 -> 97.635 | K19: =D19*(1.15^C19) -> 107305.74
A20: Esporte Total | B20: 89.9 | C20: -0.5 | D20: 75000 | E20: =B20*0.85 -> 76.415 | F20: =D20*(0.85^C20) -> 81348.922 | G20: =E20*F20/1000000 -> 6.2162779 | H20: =B20 -> 89.9 | I20: =B20*D20/1000000 -> 6.7425 | J20: =B20*1.15 -> 103.385 | K20: =D20*(1.15^C20) -> 69937.861
A21: Futebol Add | B21: 39.9 | C21: -0.45 | D21: 42000 | E21: =B21*0.85 -> 33.915 | F21: =D21*(0.85^C21) -> 45186.715 | G21: =E21*F21/1000000 -> 1.5325075 | H21: =B21 -> 39.9 | I21: =B21*D21/1000000 -> 1.6758 | J21: =B21*1.15 -> 45.885 | K21: =D21*(1.15^C21) -> 39439.851
A22: TOTAL | G22: =SUM(G16:G21) -> 54.07569 | I22: =SUM(I16:I21) -> 57.072

Sheet Pricing_Simulator
A1: SIMULADOR INTERATIVO DE PRICING — IMPACTO DE MUDANÇA DE PREÇO EM RECEITA E ASSINANTES
A2: INSTRUÇÕES: Altere as células AZUIS (Novo Preço Proposto) e veja o impacto automático em Assinantes e Receita. Use para decisões de reajuste.
A4: PAINEL DE CONTROLE — ALTERE OS INPUTS ABAIXO (células azuis)
A5: Pacote | B5: Preço Atual (R$) | C5: Assinantes Atuais | D5: Elasticidade β (da aba Elasticity) | E5: NOVO PREÇO PROPOSTO (R$) | F5: Variação de Preço % | G5: Variação Demanda % | H5: Novos Assinantes | I5: Receita Atual (R$/mês) | J5: Nova Receita (R$/mês)
A6: Futebol | B6: 89.9 | C6: 95000 | D6: -0.45 | E6: 94.9 | F6: =(E6-B6)/B6 -> 0.055617353 | G6: =D6*F6 -> -0.025027809 | H6: =ROUND(C6*(1+G6),0) -> 92622 | I6: =B6*C6 -> 8540500 | J6: =E6*H6 -> 8789827.8
A7: MMA/Combate | B7: 64.9 | C7: 42000 | D7: -0.62 | E7: 69.9 | F7: =(E7-B7)/B7 -> 0.077041602 | G7: =D7*F7 -> -0.047765794 | H7: =ROUND(C7*(1+G7),0) -> 39994 | I7: =B7*C7 -> 2725800 | J7: =E7*H7 -> 2795580.6
A8: Familia | B8: 129.9 | C8: 210000 | D8: -0.78 | E8: 139.9 | F8: =(E8-B8)/B8 -> 0.076982294 | G8: =D8*F8 -> -0.060046189 | H8: =ROUND(C8*(1+G8),0) -> 197390 | I8: =B8*C8 -> 27279000 | J8: =E8*H8 -> 27614861
A9: Series/Filmes | B9: 49.9 | C9: 68000 | D9: -1.35 | E9: 54.9 | F9: =(E9-B9)/B9 -> 0.1002004 | G9: =D9*F9 -> -0.13527054 | H9: =ROUND(C9*(1+G9),0) -> 58802 | I9: =B9*C9 -> 3393200 | J9: =E9*H9 -> 3228229.8
A10: Infantil | B10: 39.9 | C10: 55000 | D10: -0.85 | E10: 44.9 | F10: =(E10-B10)/B10 -> 0.12531328 | G10: =D10*F10 -> -0.10651629 | H10: =ROUND(C10*(1+G10),0) -> 49142 | I10: =B10*C10 -> 2194500 | J10: =E10*H10 -> 2206475.8
A11: Bundle_Plus | B11: 179.9 | C11: 95000 | D11: -0.55 | E11: 189.9 | F11: =(E11-B11)/B11 -> 0.055586437 | G11: =D11*F11 -> -0.03057254 | H11: =ROUND(C11*(1+G11),0) -> 92096 | I11: =B11*C11 -> 17090500 | J11: =E11*H11 -> 17489030
A12: TOTAL PORTFÓLIO | C12: =SUM(C6:C11) -> 565000 | H12: =SUM(H6:H11) -> 530046 | I12: =SUM(I6:I11) -> 61223500 | J12: =SUM(J6:J11) -> 62124005
A14: RESUMO DO IMPACTO DA MUDANÇA DE PREÇO PROPOSTA
A15: Variação Total de Receita (R$/mês): | G15: =J12-I12 -> 900505.4
A16: Variação Total de Assinantes: | G16: =H12-C12 -> -34954
A17: Variação % de Receita: | G17: =(J12-I12)/I12 -> 0.014708493
A18: Receita Incremental Anualizada: | G18: =(J12-I12)*12 -> 10806065

Sheet Dashboard
A1: CLARO TV+ — PRICING & PACKAGING OPTIMIZATION | DASHBOARD EXECUTIVO
A2: Visão consolidada de elasticidade, WTP e oportunidade de receita por pacote | Fonte: Abas Elasticity_Model, WTP_Conjoint, Pricing_Simulator
A4: KPIs CHAVE DE PRICING
A5: Receita Mensal Atual | D5: Receita com Preços Propostos | G5: Ganho Mensal Estimado | J5: Ganho Anualizado
A6: =Pricing_Simulator!I12 -> 61223500 | D6: =Pricing_Simulator!J12 -> 62124005 | G6: =Pricing_Simulator!J12-Pricing_Simulator!I12 -> 900505.4 | J6: =(Pricing_Simulator!J12-Pricing_Simulator!I12)*12 -> 10806065
A9: MAPA DE ELASTICIDADE E OPORTUNIDADE POR PACOTE
A10: Pacote | B10: Preço Atual | C10: Elast. β | D10: Classificação | E10: WTP Ótimo | F10: Preço Proposto | G10: Var. Preço % | H10: Var. Assin. % | I10: Receita Atual | J10: Receita Proposta | K10: Delta R$ | L10: Ação
A11: Futebol | B11: =Pricing_Simulator!B6 -> 89.9 | C11: =Elasticity_Model!D12 -> -0.45 | D11: =Elasticity_Model!I12 -> Inelástico | E11: =WTP_Conjoint!J12 -> 92.5 | F11: =Pricing_Simulator!E6 -> 94.9 | G11: =Pricing_Simulator!F6 -> 0.055617353 | H11: =Pricing_Simulator!G6 -> -0.025027809 | I11: =Pricing_Simulator!I6 -> 8540500 | J11: =Pricing_Simulator!J6 -> 8789827.8 | K11: =J11-I11 -> 249327.8 | L11: =_xlfn.IFS(G11>0.05,"↑ Reajuste",G11<-0.05,"↓ Reduzir",TRUE(),"= Manter") -> ↑ Reajuste
A12: MMA/Combate | B12: =Pricing_Simulator!B7 -> 64.9 | C12: =Elasticity_Model!D13 -> -0.62 | D12: =Elasticity_Model!I13 -> Inelástico | E12: =WTP_Conjoint!J13 -> 67.5 | F12: =Pricing_Simulator!E7 -> 69.9 | G12: =Pricing_Simulator!F7 -> 0.077041602 | H12: =Pricing_Simulator!G7 -> -0.047765794 | I12: =Pricing_Simulator!I7 -> 2725800 | J12: =Pricing_Simulator!J7 -> 2795580.6 | K12: =J12-I12 -> 69780.6 | L12: =_xlfn.IFS(G12>0.05,"↑ Reajuste",G12<-0.05,"↓ Reduzir",TRUE(),"= Manter") -> ↑ Reajuste
A13: Familia | B13: =Pricing_Simulator!B8 -> 129.9 | C13: =Elasticity_Model!D14 -> -0.78 | D13: =Elasticity_Model!I14 -> Inelástico | E13: =WTP_Conjoint!J14 -> 122.5 | F13: =Pricing_Simulator!E8 -> 139.9 | G13: =Pricing_Simulator!F8 -> 0.076982294 | H13: =Pricing_Simulator!G8 -> -0.060046189 | I13: =Pricing_Simulator!I8 -> 27279000 | J13: =Pricing_Simulator!J8 -> 27614861 | K13: =J13-I13 -> 335861 | L13: =_xlfn.IFS(G13>0.05,"↑ Reajuste",G13<-0.05,"↓ Reduzir",TRUE(),"= Manter") -> ↑ Reajuste
A14: Series/Filmes | B14: =Pricing_Simulator!B9 -> 49.9 | C14: =Elasticity_Model!D15 -> -1.35 | D14: =Elasticity_Model!I15 -> Elástico | E14: =WTP_Conjoint!J15 -> 53.5 | F14: =Pricing_Simulator!E9 -> 54.9 | G14: =Pricing_Simulator!F9 -> 0.1002004 | H14: =Pricing_Simulator!G9 -> -0.13527054 | I14: =Pricing_Simulator!I9 -> 3393200 | J14: =Pricing_Simulator!J9 -> 3228229.8 | K14: =J14-I14 -> -164970.2 | L14: =_xlfn.IFS(G14>0.05,"↑ Reajuste",G14<-0.05,"↓ Reduzir",TRUE(),"= Manter") -> ↑ Reajuste
A15: Infantil | B15: =Pricing_Simulator!B10 -> 39.9 | C15: =Elasticity_Model!D16 -> -0.85 | D15: =Elasticity_Model!I16 -> Inelástico | E15: =WTP_Conjoint!J16 -> 45 | F15: =Pricing_Simulator!E10 -> 44.9 | G15: =Pricing_Simulator!F10 -> 0.12531328 | H15: =Pricing_Simulator!G10 -> -0.10651629 | I15: =Pricing_Simulator!I10 -> 2194500 | J15: =Pricing_Simulator!J10 -> 2206475.8 | K15: =J15-I15 -> 11975.8 | L15: =_xlfn.IFS(G15>0.05,"↑ Reajuste",G15<-0.05,"↓ Reduzir",TRUE(),"= Manter") -> ↑ Reajuste
A16: Bundle_Plus | B16: =Pricing_Simulator!B11 -> 179.9 | C16: =Elasticity_Model!D17 -> -0.55 | D16: =Elasticity_Model!I17 -> Inelástico | E16: =WTP_Conjoint!J17 -> 170 | F16: =Pricing_Simulator!E11 -> 189.9 | G16: =Pricing_Simulator!F11 -> 0.055586437 | H16: =Pricing_Simulator!G11 -> -0.03057254 | I16: =Pricing_Simulator!I11 -> 17090500 | J16: =Pricing_Simulator!J11 -> 17489030 | K16: =J16-I16 -> 398530.4 | L16: =_xlfn.IFS(G16>0.05,"↑ Reajuste",G16<-0.05,"↓ Reduzir",TRUE(),"= Manter") -> ↑ Reajuste
A19: METODOLOGIA: Elasticidade estimada via regressão log-log (ln Q = α + β·ln P). WTP via Van Westendorp. Preço ótimo = média(Q2, Q3) do survey. Células azuis = inputs editáveis pelo usuário.
