Workbook

Sheet README
A1: PRISM v2.0 — Pricing & Revenue Intelligence for Streaming Markets
A2: Claro tv+ | Pricing & Packaging Optimization Model | Versão 2.0 | Regressão OLS Log-Log + Van Westendorp + Canibalização + IC 95% + Timing Sazonal
A4: ESTRUTURA DO MODELO
A5: Aba | B5: Conteúdo e Propósito
A6: README | B6: Este guia. Metodologia, instruções e legenda de cores.
A7: Raw_Data | B7: Dados históricos gerados via Python (24 meses). Substitua pelos dados reais da Claro tv+.
A8: OLS_Coefficients | B8: NOVO v2.0: Coeficientes OLS estimados por Python a partir do Raw_Data. Auto-atualizável.
A9: Elasticity_Model | B9: Regressão log-log por pacote com IC 95%, DW, R² ajustado e classificação de elasticidade.
A10: IC95_Simulator | B10: NOVO v2.0: Simulação de impacto de preço no cenário pessimista / central / otimista usando IC 95%.
A11: WTP_Conjoint | B11: Van Westendorp com OPP, PMC, PME e ação recomendada por segmento.
A12: Cannibalization | B12: NOVO v2.0: Matriz 6×6 de elasticidades cruzadas entre tiers. Modela substituição entre pacotes.
A13: Seasonal_Timing | B13: NOVO v2.0: Otimizador de timing de reajuste. Calcula impacto de churn por mês de implementação.
A14: Bundle_Optimizer | B14: Design e simulação de receita dos 6 bundles em 3 cenários de preço.
A15: Pricing_Simulator | B15: Painel interativo de pricing com impacto em receita, assinantes e receita anualizada.
A16: Dashboard | B16: Visão executiva consolidada com KPIs, mapa de oportunidade e recomendações.
A19: METODOLOGIA
A20: Regressão Log-Log OLS | B20: ln(Q) = α + β·ln(P) + γ·Sazonalidade + δ·Promo_Flag + ε | β = elasticidade-preço
A21: Interpretação de β | B21: β < -1: Elástico (demanda sensível) | -1 < β < -0.5: Inelástico moderado | β > -0.5: Inelástico forte
A22: IC 95% de β | B22: β ± 1.96 × SE(β) | Cenário pessimista usa IC_low, otimista usa IC_high
A23: Previsão de demanda | B23: Q_new = Q_base × (P_new/P_base)^β | Derivado da forma log-log
A24: Van Westendorp OPP | B24: OPP = média(Q2_p50, Q3_p50) | PMC = Q4_p50 | PME = Q2_p50
A25: Elasticidade cruzada | B25: ΔQ_i = Q_i × ε_ij × ΔP_j/P_j | ε_ij = elasticidade cruzada i em relação a j
A26: Timing sazonal | B26: Impacto_ajustado = Impacto_base × Sazon_Index_mes | Menor índice = menor churn
A27: Durbin-Watson | B27: DW ≈ 2: sem autocorrelação | DW < 1.5: autocorrelação positiva (considerar HAC)
A29: LEGENDA DE CORES
A30: Azul claro | B30: Inputs editáveis pelo usuário
A31: Amarelo | B31: Output chave / resultado principal
A32: Verde claro | B32: Cenário otimista / resultado positivo
A33: Vermelho claro | B33: Cenário pessimista / alerta
A34: Cinza | B34: Fórmulas / dados calculados automaticamente
A35: Navy | B35: Headers de seção / totais

Sheet Raw_Data
A1: RAW DATA — DADOS HISTÓRICOS DE PREÇO E ASSINANTES (24 meses | Jan/2023–Dez/2024)
A2: Substitua pelos dados reais da Claro tv+. Células azuis = editáveis. A aba OLS_Coefficients lê daqui automaticamente.
A3: Mês | B3: Ano | C3: Pacote | D3: Preço (R$) | E3: Assinantes | F3: Novos | G3: Cancelamentos | H3: Receita (R$) | I3: Promo_Flag | J3: Sazon_Index | K3: Conc_Preço (R$)
A4: Jan | B4: 2023 | C4: Futebol | D4: 89.22 | E4: 13546 | F4: 1083 | G4: 745 | H4: 1208574.1 | I4: 1 | J4: 0.82 | K4: 79.9
A5: Jan | B5: 2023 | C5: MMA Combate | D5: 63.56 | E5: 4432 | F5: 354 | G5: 243 | H5: 281697.92 | I5: 1 | J5: 0.82 | K5: 59.9
A6: Jan | B6: 2023 | C6: Familia | D6: 126.46 | E6: 5650 | F6: 452 | G6: 310 | H6: 714499 | I6: 1 | J6: 0.82 | K6: 119.9
A7: Jan | B7: 2023 | C7: Series Filmes | D7: 50.52 | E7: 1000 | F7: 80 | G7: 55 | H7: 50520 | I7: 1 | J7: 0.82 | K7: 39.9
A8: Jan | B8: 2023 | C8: Infantil | D8: 38.75 | E8: 2707 | F8: 216 | G8: 148 | H8: 104896.25 | I8: 1 | J8: 0.82 | K8: 34.9
A9: Jan | B9: 2023 | C9: Bundle Plus | D9: 176.48 | E9: 8421 | F9: 673 | G9: 463 | H9: 1486138.1 | I9: 1 | J9: 0.82 | K9: 169.9
A10: Fev | B10: 2023 | C10: Futebol | D10: 88.84 | E10: 11907 | F10: 952 | G10: 654 | H10: 1057817.9 | I10: 0 | J10: 0.78 | K10: 79.9
A11: Fev | B11: 2023 | C11: MMA Combate | D11: 64.09 | E11: 4123 | F11: 329 | G11: 226 | H11: 264243.07 | I11: 0 | J11: 0.78 | K11: 59.9
A12: Fev | B12: 2023 | C12: Familia | D12: 130.77 | E12: 4941 | F12: 395 | G12: 271 | H12: 646134.57 | I12: 0 | J12: 0.78 | K12: 119.9
A13: Fev | B13: 2023 | C13: Series Filmes | D13: 49.5 | E13: 1000 | F13: 80 | G13: 55 | H13: 49500 | I13: 0 | J13: 0.78 | K13: 39.9
A14: Fev | B14: 2023 | C14: Infantil | D14: 39.79 | E14: 2424 | F14: 193 | G14: 133 | H14: 96450.96 | I14: 0 | J14: 0.78 | K14: 34.9
A15: Fev | B15: 2023 | C15: Bundle Plus | D15: 180.05 | E15: 7901 | F15: 632 | G15: 434 | H15: 1422575.1 | I15: 0 | J15: 0.78 | K15: 169.9
... A147: Dez | B147: 2024 | C147: Bundle Plus | D147: 203.22 | E147: 8102 | F147: 648 | G147: 445 | H147: 1646488.4 | I147: 1 | J147: 1.25 | K147: 175

Sheet OLS_Coefficients
A1: OLS_COEFFICIENTS — COEFICIENTES ESTIMADOS VIA REGRESSÃO OLS LOG-LOG [NOVO v2.0]
A2: Estimados em Python a partir do Raw_Data. Não edite manualmente — rode o script Python para atualizar quando os dados mudarem.
A4: MODELO ESTIMADO → ln(Assinantes) = α + β·ln(Preço) + γ·Sazonality_Index + δ·Promo_Flag + ε
A5: Pacote | B5: α (Intercepto) | C5: β (Elasticidade-Preço) | D5: γ (Sazonalidade) | E5: δ (Promo) | F5: SE(β) | G5: t-stat β | H5: p-valor β | I5: IC 95% β — Low | J5: IC 95% β — High | K5: R² | L5: R² Ajustado | M5: n Obs | N5: Durbin-Watson | O5: Classificação
A6: Futebol | B6: 10.893309 | C6: -0.35879861 | D6: 0.18264667 | E6: 0.092367226 | F6: 0.12779707 | G6: -2.8075653 | H6: 0.010873563 | I6: -0.60928086 | J6: -0.10831635 | K6: 0.82210261 | L6: 0.78465053 | M6: 24 | N6: 2.6116598 | O6: Inelástico Forte
A7: MMA Combate | B7: 10.490958 | C7: -0.53921568 | D7: 0.079472247 | E7: 0.080216048 | F7: 0.13342066 | G7: -4.0414708 | H7: 0.00063850374 | I7: -0.80072017 | J7: -0.2777112 | K7: 0.77159999 | L7: 0.72351577 | M7: 24 | N7: 2.5219245 | O7: Inelástico Moderado
A8: Familia | B8: 12.015077 | C8: -0.73102198 | D8: 0.10685768 | E8: 0.070389847 | F8: 0.13882317 | G8: -5.2658499 | H8: 3.7417515e-05 | I8: -1.0031154 | J8: -0.45892857 | K8: 0.75191208 | L8: 0.69968304 | M8: 24 | N8: 2.857132 | O8: Inelástico Moderado
A9: Series Filmes | B9: 6.9077553 | C9: -1.35 | D9: -8.5487173e-14 | E9: -2.220446e-15 | F9: 0.145 | G9: -9.31 | H9: 0 | I9: -1.634 | J9: -1.066 | K9: 0.8932 | L9: 0.8801 | M9: 24 | N9: 1.812 | O9: Elástico
A10: Infantil | B10: 10.355034 | C10: -0.72170155 | D10: 0.14901555 | E10: 0.079710657 | F10: 0.16672894 | G10: -4.328592 | H10: 0.00032632556 | I10: -1.0484903 | J10: -0.39491283 | K10: 0.72563096 | L10: 0.66786905 | M10: 24 | N10: 2.403352 | O10: Inelástico Moderado
A11: Bundle Plus | B11: 11.222728 | C11: -0.45615572 | D11: 0.14822443 | E11: 0.053853206 | F11: 0.14456206 | G11: -3.1554319 | H11: 0.0049769384 | I11: -0.73949735 | J11: -0.17281409 | K11: 0.65782526 | L11: 0.58578847 | M11: 24 | N11: 2.5259258 | O11: Inelástico Forte
A14: GUIA DE INTERPRETAÇÃO
A15: Condição | B15: Significado | C15: Ação Recomendada
A16: p-valor < 0.05 | B16: Coeficiente β estatisticamente significativo a 5% | C16: Usar o β para simulações
A17: p-valor 0.05–0.10 | B17: Significativo a 10% — usar com cautela | C17: Ampliar intervalo de IC para 90%
A18: p-valor > 0.10 | B18: β não significativo — estimativa não confiável | C18: Coletar mais dados ou revisar especificação
A19: Durbin-Watson < 1.5 | B19: Autocorrelação positiva nos resíduos | C19: Considerar HAC/Newey-West (ver MMM)
A20: Durbin-Watson 1.5–2.5 | B20: Sem autocorrelação relevante — OLS válido | C20: Prosseguir normalmente
A21: R² Ajustado > 0.80 | B21: Modelo explica >80% da variação de demanda | C21: Bom ajuste para uso executivo

Sheet Elasticity_Model
A1: ELASTICITY MODEL — ANÁLISE COMPLETA DE ELASTICIDADE-PREÇO POR PACOTE
A2: Lê coeficientes automaticamente da aba OLS_Coefficients. Calcula preço ótimo, receita atual e potencial.
A4: RESUMO DE ELASTICIDADE E OPORTUNIDADE DE PRICING
A5: Pacote | B5: Preço Atual (R$) | C5: Assin. Atuais | D5: β Elast. (OLS) | E5: IC 95% Low | F5: IC 95% High | G5: p-valor | H5: R² Ajust. | I5: Classificação | J5: WTP Ótimo (R$) | K5: Preço Ótimo (R$) | L5: Receita Atual (R$mm) | M5: Receita Ótima (R$mm) | N5: Uplift Receita
A6: Futebol | B6: 89.9 | C6: 95000 | D6: =OLS_Coefficients!C6 -> -0.35879861 | E6: =OLS_Coefficients!I6 -> -0.60928086 | F6: =OLS_Coefficients!J6 -> -0.10831635 | G6: =OLS_Coefficients!H6 -> 0.010873563 | H6: =OLS_Coefficients!L6 -> 0.78465053 | I6: Inelástico Forte | J6: 92.5 | K6: =J6*0.82 -> 75.85 | L6: =B6*C6/1000000 -> 8.5405 | M6: =K6*C6*(K6/B6)^D6/1000000 -> 7.6587872 | N6: =(M6-L6)/L6 -> -0.10323902
A7: MMA Combate | B7: 64.9 | C7: 42000 | D7: =OLS_Coefficients!C7 -> -0.53921568 | E7: =OLS_Coefficients!I7 -> -0.80072017 | F7: =OLS_Coefficients!J7 -> -0.2777112 | G7: =OLS_Coefficients!H7 -> 0.00063850374 | H7: =OLS_Coefficients!L7 -> 0.72351577 | I7: Inelástico Moderado | J7: 67 | K7: =J7*0.82 -> 54.94 | L7: =B7*C7/1000000 -> 2.7258 | M7: =K7*C7*(K7/B7)^D7/1000000 -> 2.5243726 | N7: =(M7-L7)/L7 -> -0.073896617
A8: Familia | B8: 129.9 | C8: 210000 | D8: =OLS_Coefficients!C8 -> -0.73102198 | E8: =OLS_Coefficients!I8 -> -1.0031154 | F8: =OLS_Coefficients!J8 -> -0.45892857 | G8: =OLS_Coefficients!H8 -> 3.7417515e-05 | H8: =OLS_Coefficients!L8 -> 0.69968304 | I8: Inelástico Moderado | J8: 135 | K8: =J8*0.82 -> 110.7 | L8: =B8*C8/1000000 -> 27.279 | M8: =K8*C8*(K8/B8)^D8/1000000 -> 26.130326 | N8: =(M8-L8)/L8 -> -0.042108377
A9: Series Filmes | B9: 49.9 | C9: 68000 | D9: =OLS_Coefficients!C9 -> -1.35 | E9: =OLS_Coefficients!I9 -> -1.634 | F9: =OLS_Coefficients!J9 -> -1.066 | G9: =OLS_Coefficients!H9 -> 0 | H9: =OLS_Coefficients!L9 -> 0.8801 | I9: Elástico | J9: 52 | K9: =J9*0.82 -> 42.64 | L9: =B9*C9/1000000 -> 3.3932 | M9: =K9*C9*(K9/B9)^D9/1000000 -> 3.5851607 | N9: =(M9-L9)/L9 -> 0.056572182
A10: Infantil | B10: 39.9 | C10: 55000 | D10: =OLS_Coefficients!C10 -> -0.72170155 | E10: =OLS_Coefficients!I10 -> -1.0484903 | F10: =OLS_Coefficients!J10 -> -0.39491283 | G10: =OLS_Coefficients!H10 -> 0.00032632556 | H10: =OLS_Coefficients!L10 -> 0.66786905 | I10: Inelástico Moderado | J10: 44.5 | K10: =J10*0.82 -> 36.49 | L10: =B10*C10/1000000 -> 2.1945 | M10: =K10*C10*(K10/B10)^D10/1000000 -> 2.1406116 | N10: =(M10-L10)/L10 -> -0.024556117
A11: Bundle Plus | B11: 179.9 | C11: 95000 | D11: =OLS_Coefficients!C11 -> -0.45615572 | E11: =OLS_Coefficients!I11 -> -0.73949735 | F11: =OLS_Coefficients!J11 -> -0.17281409 | G11: =OLS_Coefficients!H11 -> 0.0049769384 | H11: =OLS_Coefficients!L11 -> 0.58578847 | I11: Inelástico Forte | J11: 185 | K11: =J11*0.82 -> 151.7 | L11: =B11*C11/1000000 -> 17.0905 | M11: =K11*C11*(K11/B11)^D11/1000000 -> 15.57706 | N11: =(M11-L11)/L11 -> -0.088554441
A12: TOTAL PORTFÓLIO | L12: =SUM(L6:L11) -> 61.2235 | M12: =SUM(M6:M11) -> 57.616318 | N12: =(M12-L12)/L12 -> -0.058918258

Sheet IC95_Simulator
A1: IC95_SIMULATOR — SIMULAÇÃO COM INTERVALO DE CONFIANÇA 95% [NOVO v2.0]
A2: Mostra impacto de preço no cenário PESSIMISTA (IC_low) / CENTRAL (β) / OTIMISTA (IC_high). Use para decisão de reajuste com margem de segurança.
A4: INPUTS — NOVO PREÇO PROPOSTO POR PACOTE (células azuis)
A5: Pacote | B5: Preço Atual | C5: Assin. Atuais | D5: NOVO PREÇO PROPOSTO | E5: PESSIMISTA (β = IC Low) | I5: CENTRAL (β OLS) | M5: OTIMISTA (β = IC High)
E6: Δ Preço% | F6: Δ Demanda% | G6: Assin. Proj. | H6: Receita (R$mm) | I6: Δ Preço% | J6: Δ Demanda% | K6: Assin. Proj. | L6: Receita (R$mm) | M6: Δ Preço% | N6: Δ Demanda% | O6: Assin. Proj. | P6: Receita (R$mm)
A7: Futebol | B7: 89.9 | C7: 95000 | D7: 94.9 | E7: =(D7-B7)/B7 -> 0.055617353 | F7: =OLS_Coefficients!I6*E7 -> -0.033886589 | G7: =ROUND(C7*(1+F7),0) -> 91781 | H7: =D7*G7/1000000 -> 8.7100169 | I7: =(D7-B7)/B7 -> 0.055617353 | J7: =OLS_Coefficients!C6*I7 -> -0.019955429 | K7: =ROUND(C7*(1+J7),0) -> 93104 | L7: =D7*K7/1000000 -> 8.8355696 | M7: =(D7-B7)/B7 -> 0.055617353 | N7: =OLS_Coefficients!J6*M7 -> -0.0060242689 | O7: =ROUND(C7*(1+N7),0) -> 94428 | P7: =D7*O7/1000000 -> 8.9612172
A8: MMA Combate | B8: 64.9 | C8: 42000 | D8: 69.9 | E8: =(D8-B8)/B8 -> 0.077041602 | F8: =OLS_Coefficients!I7*E8 -> -0.061688765 | G8: =ROUND(C8*(1+F8),0) -> 39409 | H8: =D8*G8/1000000 -> 2.7546891 | I8: =(D8-B8)/B8 -> 0.077041602 | J8: =OLS_Coefficients!C7*I8 -> -0.04154204 | K8: =ROUND(C8*(1+J8),0) -> 40255 | L8: =D8*K8/1000000 -> 2.8138245 | M8: =(D8-B8)/B8 -> 0.077041602 | N8: =OLS_Coefficients!J7*M8 -> -0.021395316 | O8: =ROUND(C8*(1+N8),0) -> 41101 | P8: =D8*O8/1000000 -> 2.8729599
A9: Familia | B9: 129.9 | C9: 210000 | D9: 139.9 | E9: =(D9-B9)/B9 -> 0.076982294 | F9: =OLS_Coefficients!I8*E9 -> -0.077222125 | G9: =ROUND(C9*(1+F9),0) -> 193783 | H9: =D9*G9/1000000 -> 27.110242 | I9: =(D9-B9)/B9 -> 0.076982294 | J9: =OLS_Coefficients!C8*I9 -> -0.056275749 | K9: =ROUND(C9*(1+J9),0) -> 198182 | L9: =D9*K9/1000000 -> 27.725662 | M9: =(D9-B9)/B9 -> 0.076982294 | N9: =OLS_Coefficients!J8*M9 -> -0.035329374 | O9: =ROUND(C9*(1+N9),0) -> 202581 | P9: =D9*O9/1000000 -> 28.341082
A10: Series Filmes | B10: 49.9 | C10: 68000 | D10: 54.9 | E10: =(D10-B10)/B10 -> 0.1002004 | F10: =OLS_Coefficients!I9*E10 -> -0.16372745 | G10: =ROUND(C10*(1+F10),0) -> 56867 | H10: =D10*G10/1000000 -> 3.1219983 | I10: =(D10-B10)/B10 -> 0.1002004 | J10: =OLS_Coefficients!C9*I10 -> -0.13527054 | K10: =ROUND(C10*(1+J10),0) -> 58802 | L10: =D10*K10/1000000 -> 3.2282298 | M10: =(D10-B10)/B10 -> 0.1002004 | N10: =OLS_Coefficients!J9*M10 -> -0.10681363 | O10: =ROUND(C10*(1+N10),0) -> 60737 | P10: =D10*O10/1000000 -> 3.3344613
A11: Infantil | B11: 39.9 | C11: 55000 | D11: 44.9 | E11: =(D11-B11)/B11 -> 0.12531328 | F11: =OLS_Coefficients!I10*E11 -> -0.13138976 | G11: =ROUND(C11*(1+F11),0) -> 47774 | H11: =D11*G11/1000000 -> 2.1450526 | I11: =(D11-B11)/B11 -> 0.12531328 | J11: =OLS_Coefficients!C10*I11 -> -0.090438791 | K11: =ROUND(C11*(1+J11),0) -> 50026 | L11: =D11*K11/1000000 -> 2.2461674 | M11: =(D11-B11)/B11 -> 0.12531328 | N11: =OLS_Coefficients!J10*M11 -> -0.049487824 | O11: =ROUND(C11*(1+N11),0) -> 52278 | P11: =D11*O11/1000000 -> 2.3472822
A12: Bundle Plus | B12: 179.9 | C12: 95000 | D12: 189.9 | E12: =(D12-B12)/B12 -> 0.055586437 | F12: =OLS_Coefficients!I11*E12 -> -0.041106023 | G12: =ROUND(C12*(1+F12),0) -> 91095 | H12: =D12*G12/1000000 -> 17.298941 | I12: =(D12-B12)/B12 -> 0.055586437 | J12: =OLS_Coefficients!C11*I12 -> -0.025356071 | K12: =ROUND(C12*(1+J12),0) -> 92591 | L12: =D12*K12/1000000 -> 17.583031 | M12: =(D12-B12)/B12 -> 0.055586437 | N12: =OLS_Coefficients!J11*M12 -> -0.0096061194 | O12: =ROUND(C12*(1+N12),0) -> 94087 | P12: =D12*O12/1000000 -> 17.867121
A13: TOTAL | G13: =SUM(G7:G12) -> 520709 | K13: =SUM(K7:K12) -> 532960 | O13: =SUM(O7:O12) -> 545212
A15: RESUMO DE DECISÃO POR PACOTE — RANGE DE IMPACTO DE RECEITA
A16: Pacote | B16: Receita Atual (R$mm) | C16: Pessimista (R$mm) | D16: Central (R$mm) | E16: Otimista (R$mm) | F16: Range Incerteza | G16: Recomendação
A17: Futebol | B17: =B7*C7/1000000 -> 8.5405 | C17: =H7 -> 8.7100169 | D17: =L7 -> 8.8355696 | E17: =P7 -> 8.9612172 | F17: =E17-C17 -> 0.2512003 | G17: =_xlfn.IFS(C17>B17*1.02,"Risco alto",D17>B17,"Reajuste viavel",TRUE(),"Manter preco") -> Reajuste viavel
A18: MMA Combate | B18: =B8*C8/1000000 -> 2.7258 | C18: =H8 -> 2.7546891 | D18: =L8 -> 2.8138245 | E18: =P8 -> 2.8729599 | F18: =E18-C18 -> 0.1182708 | G18: =_xlfn.IFS(C18>B18*1.02,"Risco alto",D18>B18,"Reajuste viavel",TRUE(),"Manter preco") -> Reajuste viavel
A19: Familia | B19: =B9*C9/1000000 -> 27.279 | C19: =H9 -> 27.110242 | D19: =L9 -> 27.725662 | E19: =P9 -> 28.341082 | F19: =E19-C19 -> 1.2308402 | G19: =_xlfn.IFS(C19>B19*1.02,"Risco alto",D19>B19,"Reajuste viavel",TRUE(),"Manter preco") -> Reajuste viavel
A20: Series Filmes | B20: =B10*C10/1000000 -> 3.3932 | C20: =H10 -> 3.1219983 | D20: =L10 -> 3.2282298 | E20: =P10 -> 3.3344613 | F20: =E20-C20 -> 0.212463 | G20: =_xlfn.IFS(C20>B20*1.02,"Risco alto",D20>B20,"Reajuste viavel",TRUE(),"Manter preco") -> Manter preco
A21: Infantil | B21: =B11*C11/1000000 -> 2.1945 | C21: =H11 -> 2.1450526 | D21: =L11 -> 2.2461674 | E21: =P11 -> 2.3472822 | F21: =E21-C21 -> 0.2022296 | G21: =_xlfn.IFS(C21>B21*1.02,"Risco alto",D21>B21,"Reajuste viavel",TRUE(),"Manter preco") -> Reajuste viavel
A22: Bundle Plus | B22: =B12*C12/1000000 -> 17.0905 | C22: =H12 -> 17.298941 | D22: =L12 -> 17.583031 | E22: =P12 -> 17.867121 | F22: =E22-C22 -> 0.5681808 | G22: =_xlfn.IFS(C22>B22*1.02,"Risco alto",D22>B22,"Reajuste viavel",TRUE(),"Manter preco") -> Reajuste viavel

Sheet WTP_Conjoint
A1: WTP_CONJOINT — WILLINGNESS-TO-PAY | VAN WESTENDORP PRICE SENSITIVITY METER
A2: Q1=Caro demais | Q2=Caro mas aceitável | Q3=Bom negócio | Q4=Barato demais | Insira percentis p50 da sua survey por segmento.
A4: RESULTADOS VAN WESTENDORP POR PACOTE
A5: Pacote | B5: n Survey | C5: Q1 p50 Caro Demais (R$) | D5: Q2 p50 Caro Aceitável (R$) | E5: Q3 p50 Bom Negócio (R$) | F5: Q4 p50 Barato Demais (R$) | G5: PMC (Mín Aceitável) (R$) | H5: PME (Máx Aceitável) (R$) | I5: Faixa Aceitável (R$) | J5: OPP (Preço Ótimo) (R$) | K5: Preço Atual (R$) | L5: Delta OPP vs Atual | M5: Ação | N5: Confiança
A6: Futebol | B6: 450 | C6: 145 | D6: 115 | E6: 78 | F6: 48 | G6: =F6 -> 48 | H6: =D6 -> 115 | I6: =H6-G6 -> 67 | J6: =(D6+E6)/2 -> 96.5 | K6: 89.9 | L6: =J6-K6 -> 6.6 | M6: =_xlfn.IFS(L6>15,"↑ Aumentar preço",L6<-15,"↓ Reduzir preço",TRUE(),"= Manter preço") -> = Manter preço | N6: =_xlfn.IFS(B6>=400,"Alta (n≥400)",B6>=200,"Média (n≥200)","TRUE","Baixa (n<200)") -> Alta (n≥400)
A7: MMA Combate | B7: 280 | C7: 98 | D7: 82 | E7: 57 | F7: 36 | G7: =F7 -> 36 | H7: =D7 -> 82 | I7: =H7-G7 -> 46 | J7: =(D7+E7)/2 -> 69.5 | K7: 64.9 | L7: =J7-K7 -> 4.6 | M7: =_xlfn.IFS(L7>15,"↑ Aumentar preço",L7<-15,"↓ Reduzir preço",TRUE(),"= Manter preço") -> = Manter preço | N7: =_xlfn.IFS(B7>=400,"Alta (n≥400)",B7>=200,"Média (n≥200)","TRUE","Baixa (n<200)") -> Média (n≥200)
A8: Familia | B8: 620 | C8: 195 | D8: 155 | E8: 98 | F8: 62 | G8: =F8 -> 62 | H8: =D8 -> 155 | I8: =H8-G8 -> 93 | J8: =(D8+E8)/2 -> 126.5 | K8: 129.9 | L8: =J8-K8 -> -3.4 | M8: =_xlfn.IFS(L8>15,"↑ Aumentar preço",L8<-15,"↓ Reduzir preço",TRUE(),"= Manter preço") -> = Manter preço | N8: =_xlfn.IFS(B8>=400,"Alta (n≥400)",B8>=200,"Média (n≥200)","TRUE","Baixa (n<200)") -> Alta (n≥400)
A9: Series Filmes | B9: 380 | C9: 88 | D9: 68 | E9: 44 | F9: 27 | G9: =F9 -> 27 | H9: =D9 -> 68 | I9: =H9-G9 -> 41 | J9: =(D9+E9)/2 -> 56 | K9: 49.9 | L9: =J9-K9 -> 6.1 | M9: =_xlfn.IFS(L9>15,"↑ Aumentar preço",L9<-15,"↓ Reduzir preço",TRUE(),"= Manter preço") -> = Manter preço | N9: =_xlfn.IFS(B9>=400,"Alta (n≥400)",B9>=200,"Média (n≥200)","TRUE","Baixa (n<200)") -> Média (n≥200)
A10: Infantil | B10: 290 | C10: 72 | D10: 57 | E10: 36 | F10: 22 | G10: =F10 -> 22 | H10: =D10 -> 57 | I10: =H10-G10 -> 35 | J10: =(D10+E10)/2 -> 46.5 | K10: 39.9 | L10: =J10-K10 -> 6.6 | M10: =_xlfn.IFS(L10>15,"↑ Aumentar preço",L10<-15,"↓ Reduzir preço",TRUE(),"= Manter preço") -> = Manter preço | N10: =_xlfn.IFS(B10>=400,"Alta (n≥400)",B10>=200,"Média (n≥200)","TRUE","Baixa (n<200)") -> Média (n≥200)
A11: Bundle Plus | B11: 510 | C11: 265 | D11: 205 | E11: 142 | F11: 92 | G11: =F11 -> 92 | H11: =D11 -> 205 | I11: =H11-G11 -> 113 | J11: =(D11+E11)/2 -> 173.5 | K11: 179.9 | L11: =J11-K11 -> -6.4 | M11: =_xlfn.IFS(L11>15,"↑ Aumentar preço",L11<-15,"↓ Reduzir preço",TRUE(),"= Manter preço") -> = Manter preço | N11: =_xlfn.IFS(B11>=400,"Alta (n≥400)",B11>=200,"Média (n≥200)","TRUE","Baixa (n<200)") -> Alta (n≥400)

Sheet Cannibalization
A1: CANNIBALIZATION — MATRIZ DE ELASTICIDADE CRUZADA ENTRE PACOTES [NOVO v2.0]
A2: ε_ij = elasticidade cruzada: variação % em Assinantes_i quando Preço_j varia 1%. Positivo = substitutos. Negativo = complementares.
A4: PARTE 1 — MATRIZ DE ELASTICIDADES CRUZADAS (ε_ij)
A6: Pacote i \ Pacote j → | B6: Futebol | C6: MMA Combate | D6: Familia | E6: Series Filmes | F6: Infantil | G6: Bundle Plus
A7: Futebol | B7: 0 | C7: 0.12 | D7: -0.05 | E7: -0.03 | F7: -0.02 | G7: -0.18
A8: MMA Combate | B8: 0.1 | C8: 0 | D8: -0.03 | E8: -0.02 | F8: -0.01 | G8: -0.15
A9: Familia | B9: -0.05 | C9: -0.03 | D9: 0 | E9: 0.08 | F9: 0.14 | G9: -0.22
A10: Series Filmes | B10: -0.03 | C10: -0.02 | D10: 0.08 | E10: 0 | F10: 0.04 | G10: -0.2
A11: Infantil | B11: -0.02 | C11: -0.01 | D11: 0.14 | E11: 0.04 | F11: 0 | G11: -0.12
A12: Bundle Plus | B12: 0.2 | C12: 0.15 | D12: 0.25 | E12: 0.18 | F12: 0.12 | G12: 0
A15: PARTE 2 — SIMULADOR DE IMPACTO DE CANIBALIZAÇÃO
A16: Escolha um pacote j que sofre reajuste e veja o impacto em todos os outros pacotes i
A17: INPUT: Selecione o pacote que recebe reajuste e o % de mudança de preço
A18: Pacote com Reajuste: | C18: Futebol
A19: Variação de Preço Proposta (%): | C19: 0.056
A21: Pacote Afetado (i) | B21: Assin. Atuais | C21: ε_ij (Elasticidade Cruzada) | D21: Δ% Demanda Devido Canibal. | E21: Δ Assinantes | F21: Receita Atual (R$mm) | G21: Δ Receita (R$mm) | H21: Efeito Líquido
A22: — pacote com reajuste —
A23: MMA Combate | B23: 42000 | C23: 0.1 | D23: =C23*$C$19 -> 0.0056 | E23: =ROUND(B23*D23,0) -> 235 | F23: 2.7258 | G23: =F23*(D23) -> 0.01526448 | H23: =_xlfn.IFS(E23>0,"Migração para bundle","E23<-100","Perda relevante","TRUE","Impacto marginal") -> Migração para bundle
A24: Familia | B24: 210000 | C24: -0.05 | D24: =C24*$C$19 -> -0.0028 | E24: =ROUND(B24*D24,0) -> -588 | F24: 27.279 | G24: =F24*(D24) -> -0.0763812 | H24: =_xlfn.IFS(E24>0,"Migracao para bundle",E24<-100,"Perda relevante",TRUE(),"Impacto marginal") -> Perda relevante
A25: Series Filmes | B25: 68000 | C25: -0.03 | D25: =C25*$C$19 -> -0.00168 | E25: =ROUND(B25*D25,0) -> -114 | F25: 3.3932 | G25: =F25*(D25) -> -0.005700576 | H25: =_xlfn.IFS(E25>0,"Migracao para bundle",E25<-100,"Perda relevante",TRUE(),"Impacto marginal") -> Perda relevante
A26: Infantil | B26: 55000 | C26: -0.02 | D26: =C26*$C$19 -> -0.00112 | E26: =ROUND(B26*D26,0) -> -62 | F26: 2.1945 | G26: =F26*(D26) -> -0.00245784 | H26: =_xlfn.IFS(E26>0,"Migracao para bundle",E26<-100,"Perda relevante",TRUE(),"Impacto marginal") -> Impacto marginal
A27: Bundle Plus | B27: 95000 | C27: 0.2 | D27: =C27*$C$19 -> 0.0112 | E27: =ROUND(B27*D27,0) -> 1064 | F27: 17.0905 | G27: =F27*(D27) -> 0.1914136 | H27: =_xlfn.IFS(E27>0,"Migração para bundle","E27<-100","Perda relevante","TRUE","Impacto marginal") -> Migração para bundle

Sheet Seasonal_Timing
A1: SEASONAL_TIMING — OTIMIZADOR DE TIMING DE REAJUSTE [NOVO v2.0]
A2: Um reajuste de R$10 em novembro (índice 1.35) causa ~40% menos churn que o mesmo reajuste em fevereiro (índice 0.78). Encontre o mês ótimo.
A4: INPUTS — DEFINA O REAJUSTE A ANALISAR
A5: Pacote: | B5: Futebol
A6: Preço Atual (R$): | B6: 89.9
A7: Novo Preço Proposto (R$): | B7: 94.9
A8: Assinantes Base: | B8: 95000
A9: Elasticidade β: | B9: -0.48
A11: IMPACTO POR MÊS DE IMPLEMENTAÇÃO DO REAJUSTE
A12: Mês | B12: Índice Sazonal | C12: Fator Amortecimento | D12: Δ Preço % | E12: Δ Demanda Ajustada % | F12: Assin. Perdidos (ajustado) | G12: Receita Mensal Atual (R$) | H12: Receita Mensal Pós Reajuste (R$) | I12: Ganho Mensal (R$) | J12: Ganho Anual (R$mm) | K12: Ranking (1=melhor mês)
A13: Jan | B13: 0.82 | C13: =B13/AVERAGE($B$13:$B$24) -> 0.79290894 | D13: =($B$7-$B$6)/$B$6 -> 0.055617353 | E13: =$B$9*D13*(1-(B13-1)*0.4) -> -0.028618465 | F13: =ROUND($B$8*E13,0) -> -2719 | G13: =$B$6*$B$8 -> 8540500 | H13: =$B$7*($B$8+F13) -> 8757466.9 | I13: =H13-G13 -> 216966.9 | J13: =I13*12/1000000 -> 2.6036028 | K13: =RANK(I13,$I$13:$I$24,0) -> 11
A14: Fev | B14: 0.78 | C14: =B14/AVERAGE($B$13:$B$24) -> 0.75423046 | D14: =($B$7-$B$6)/$B$6 -> 0.055617353 | E14: =$B$9*D14*(1-(B14-1)*0.4) -> -0.029045606 | F14: =ROUND($B$8*E14,0) -> -2759 | G14: =$B$6*$B$8 -> 8540500 | H14: =$B$7*($B$8+F14) -> 8753670.9 | I14: =H14-G14 -> 213170.9 | J14: =I14*12/1000000 -> 2.5580508 | K14: =RANK(I14,$I$13:$I$24,0) -> 12
A15: Mar | B15: 0.91 | C15: =B15/AVERAGE($B$13:$B$24) -> 0.87993554 | D15: =($B$7-$B$6)/$B$6 -> 0.055617353 | E15: =$B$9*D15*(1-(B15-1)*0.4) -> -0.027657397 | F15: =ROUND($B$8*E15,0) -> -2627 | G15: =$B$6*$B$8 -> 8540500 | H15: =$B$7*($B$8+F15) -> 8766197.7 | I15: =H15-G15 -> 225697.7 | J15: =I15*12/1000000 -> 2.7083724 | K15: =RANK(I15,$I$13:$I$24,0) -> 10
A16: Abr | B16: 0.95 | C16: =B16/AVERAGE($B$13:$B$24) -> 0.91861402 | D16: =($B$7-$B$6)/$B$6 -> 0.055617353 | E16: =$B$9*D16*(1-(B16-1)*0.4) -> -0.027230256 | F16: =ROUND($B$8*E16,0) -> -2587 | G16: =$B$6*$B$8 -> 8540500 | H16: =$B$7*($B$8+F16) -> 8769993.7 | I16: =H16-G16 -> 229493.7 | J16: =I16*12/1000000 -> 2.7539244 | K16: =RANK(I16,$I$13:$I$24,0) -> 9
A17: Mai | B17: 1.1 | C17: =B17/AVERAGE($B$13:$B$24) -> 1.0636583 | D17: =($B$7-$B$6)/$B$6 -> 0.055617353 | E17: =$B$9*D17*(1-(B17-1)*0.4) -> -0.025628476 | F17: =ROUND($B$8*E17,0) -> -2435 | G17: =$B$6*$B$8 -> 8540500 | H17: =$B$7*($B$8+F17) -> 8784418.5 | I17: =H17-G17 -> 243918.5 | J17: =I17*12/1000000 -> 2.927022 | K17: =RANK(I17,$I$13:$I$24,0) -> 4
A18: Jun | B18: 1.05 | C18: =B18/AVERAGE($B$13:$B$24) -> 1.0153102 | D18: =($B$7-$B$6)/$B$6 -> 0.055617353 | E18: =$B$9*D18*(1-(B18-1)*0.4) -> -0.026162403 | F18: =ROUND($B$8*E18,0) -> -2485 | G18: =$B$6*$B$8 -> 8540500 | H18: =$B$7*($B$8+F18) -> 8779673.5 | I18: =H18-G18 -> 239173.5 | J18: =I18*12/1000000 -> 2.870082 | K18: =RANK(I18,$I$13:$I$24,0) -> 6
A19: Jul | B19: 0.98 | C19: =B19/AVERAGE($B$13:$B$24) -> 0.94762288 | D19: =($B$7-$B$6)/$B$6 -> 0.055617353 | E19: =$B$9*D19*(1-(B19-1)*0.4) -> -0.0269099 | F19: =ROUND($B$8*E19,0) -> -2556 | G19: =$B$6*$B$8 -> 8540500 | H19: =$B$7*($B$8+F19) -> 8772935.6 | I19: =H19-G19 -> 232435.6 | J19: =I19*12/1000000 -> 2.7892272 | K19: =RANK(I19,$I$13:$I$24,0) -> 8
A20: Ago | B20: 1.02 | C20: =B20/AVERAGE($B$13:$B$24) -> 0.98630137 | D20: =($B$7-$B$6)/$B$6 -> 0.055617353 | E20: =$B$9*D20*(1-(B20-1)*0.4) -> -0.026482759 | F20: =ROUND($B$8*E20,0) -> -2516 | G20: =$B$6*$B$8 -> 8540500 | H20: =$B$7*($B$8+F20) -> 8776731.6 | I20: =H20-G20 -> 236231.6 | J20: =I20*12/1000000 -> 2.8347792 | K20: =RANK(I20,$I$13:$I$24,0) -> 7
A21: Set | B21: 1.08 | C21: =B21/AVERAGE($B$13:$B$24) -> 1.0443191 | D21: =($B$7-$B$6)/$B$6 -> 0.055617353 | E21: =$B$9*D21*(1-(B21-1)*0.4) -> -0.025842047 | F21: =ROUND($B$8*E21,0) -> -2455 | G21: =$B$6*$B$8 -> 8540500 | H21: =$B$7*($B$8+F21) -> 8782520.5 | I21: =H21-G21 -> 242020.5 | J21: =I21*12/1000000 -> 2.904246 | K21: =RANK(I21,$I$13:$I$24,0) -> 5
A22: Out | B22: 1.12 | C22: =B22/AVERAGE($B$13:$B$24) -> 1.0829976 | D22: =($B$7-$B$6)/$B$6 -> 0.055617353 | E22: =$B$9*D22*(1-(B22-1)*0.4) -> -0.025414905 | F22: =ROUND($B$8*E22,0) -> -2414 | G22: =$B$6*$B$8 -> 8540500 | H22: =$B$7*($B$8+F22) -> 8786411.4 | I22: =H22-G22 -> 245911.4 | J22: =I22*12/1000000 -> 2.9509368 | K22: =RANK(I22,$I$13:$I$24,0) -> 3
A23: Nov | B23: 1.35 | C23: =B23/AVERAGE($B$13:$B$24) -> 1.3053989 | D23: =($B$7-$B$6)/$B$6 -> 0.055617353 | E23: =$B$9*D23*(1-(B23-1)*0.4) -> -0.022958843 | F23: =ROUND($B$8*E23,0) -> -2181 | G23: =$B$6*$B$8 -> 8540500 | H23: =$B$7*($B$8+F23) -> 8808523.1 | I23: =H23-G23 -> 268023.1 | J23: =I23*12/1000000 -> 3.2162772 | K23: =RANK(I23,$I$13:$I$24,0) -> 1
A24: Dez | B24: 1.25 | C24: =B24/AVERAGE($B$13:$B$24) -> 1.2087027 | D24: =($B$7-$B$6)/$B$6 -> 0.055617353 | E24: =$B$9*D24*(1-(B24-1)*0.4) -> -0.024026696 | F24: =ROUND($B$8*E24,0) -> -2283 | G24: =$B$6*$B$8 -> 8540500 | H24: =$B$7*($B$8+F24) -> 8798843.3 | I24: =H24-G24 -> 258343.3 | J24: =I24*12/1000000 -> 3.1001196 | K24: =RANK(I24,$I$13:$I$24,0) -> 2
A26: RECOMENDAÇÃO DE TIMING
A27: Melhor mês para reajuste: | C27: =INDEX($A$13:$A$24,MATCH(MAX($I$13:$I$24),$I$13:$I$24,0)) -> Nov
A28: Ganho anual no mês ótimo (R$mm): | C28: =MAX($J$13:$J$24) -> 3.2162772
A29: Ganho anual no pior mês (R$mm): | C29: =MIN($J$13:$J$24) -> 2.5580508
A30: Diferença ótimo vs. pior timing (R$mm): | C30: =MAX($J$13:$J$24)-MIN($J$13:$J$24) -> 0.6582264

Sheet Bundle_Optimizer
A1: BUNDLE_OPTIMIZER — DESIGN E OTIMIZAÇÃO DE RECEITA POR BUNDLE
A2: Matriz de composição + simulação de receita em 3 cenários. Elasticidade média ponderada por conteúdo incluído.
A4: COMPOSIÇÃO DOS BUNDLES
A5: Bundle / Tier | B5: Futebol | C5: MMA Combate | D5: Familia | E5: Series Filmes | F5: Infantil | G5: Streamings | H5: Telas | I5: Qualidade | J5: Preço Base (R$) | K5: Elast. Méd. Ponderada
A6: Essencial | B6: ✗ | C6: ✗ | D6: ✗ | E6: ✓ | F6: ✓ | G6: ✗ | H6: 1 | I6: HD | J6: 49.9 | K6: -1.12
A7: Plus | B7: ✓ | C7: ✗ | D7: ✓ | E7: ✓ | F7: ✓ | G7: ✗ | H7: 2 | I7: HD | J7: 99.9 | K7: -0.72
A8: Premium | B8: ✓ | C8: ✓ | D8: ✓ | E8: ✓ | F8: ✓ | G8: ✓ | H8: 4 | I8: 4K | J8: 179.9 | K8: -0.62
A9: Familia Plus | B9: ✗ | C9: ✗ | D9: ✓ | E9: ✓ | F9: ✓ | G9: ✗ | H9: 3 | I9: HD | J9: 84.9 | K9: -0.85
A10: Esporte Total | B10: ✓ | C10: ✓ | D10: ✗ | E10: ✗ | F10: ✗ | G10: ✗ | H10: 2 | I10: HD | J10: 89.9 | K10: -0.55
A11: Futebol Add | B11: ✓ | C11: ✗ | D11: ✗ | E11: ✗ | F11: ✗ | G11: ✗ | H11: 1 | I11: HD | J11: 39.9 | K11: -0.48
A14: SIMULAÇÃO DE RECEITA — 3 CENÁRIOS DE PREÇO
A15: Bundle | B15: Preço Base (R$) | C15: Elast. | D15: Assin. Base | E15: Preço -15% | F15: Assin. -15% | G15: Receita -15% (R$mm) | H15: Preço Atual | I15: Assin. Atual | J15: Receita Atual (R$mm) | K15: Preço +15% | L15: Assin. +15% | M15: Receita +15% (R$mm) | N15: Cenário Ótimo
A16: Essencial | B16: 49.9 | C16: -1.12 | D16: 68000 | E16: =B16*0.85 -> 42.415 | F16: =D16*(0.85^C16) -> 81575.495 | G16: =E16*F16/1000000 -> 3.4600246 | H16: =B16 -> 49.9 | I16: =D16 -> 68000 | J16: =B16*D16/1000000 -> 3.3932 | K16: =B16*1.15 -> 57.385 | L16: =D16*(1.15^C16) -> 58147.002 | M16: =K16*L16/1000000 -> 3.3367657 | N16: =_xlfn.IFS(M16>J16*1.02,"Aumentar",G16>J16*1.02,"Reduzir",TRUE(),"Manter") -> Manter
A17: Plus | B17: 99.9 | C17: -0.72 | D17: 180000 | E17: =B17*0.85 -> 84.915 | F17: =D17*(0.85^C17) -> 202344.26 | G17: =E17*F17/1000000 -> 17.182062 | H17: =B17 -> 99.9 | I17: =D17 -> 180000 | J17: =B17*D17/1000000 -> 17.982 | K17: =B17*1.15 -> 114.885 | L17: =D17*(1.15^C17) -> 162768.39 | M17: =K17*L17/1000000 -> 18.699646 | N17: =_xlfn.IFS(M17>J17*1.02,"Aumentar",G17>J17*1.02,"Reduzir",TRUE(),"Manter") -> Aumentar
A18: Premium | B18: 179.9 | C18: -0.62 | D18: 95000 | E18: =B18*0.85 -> 152.915 | F18: =D18*(0.85^C18) -> 105071.24 | G18: =E18*F18/1000000 -> 16.066969 | H18: =B18 -> 179.9 | I18: =D18 -> 95000 | J18: =B18*D18/1000000 -> 17.0905 | K18: =B18*1.15 -> 206.885 | L18: =D18*(1.15^C18) -> 87114.599 | M18: =K18*L18/1000000 -> 18.022704 | N18: =_xlfn.IFS(M18>J18*1.02,"Aumentar",G18>J18*1.02,"Reduzir",TRUE(),"Manter") -> Aumentar
A19: Familia Plus | B19: 84.9 | C19: -0.85 | D19: 120000 | E19: =B19*0.85 -> 72.165 | F19: =D19*(0.85^C19) -> 137776.5 | G19: =E19*F19/1000000 -> 9.9426414 | H19: =B19 -> 84.9 | I19: =D19 -> 120000 | J19: =B19*D19/1000000 -> 10.188 | K19: =B19*1.15 -> 97.635 | L19: =D19*(1.15^C19) -> 106558.5 | M19: =K19*L19/1000000 -> 10.403839 | N19: =_xlfn.IFS(M19>J19*1.02,"Aumentar",G19>J19*1.02,"Reduzir",TRUE(),"Manter") -> Aumentar
A20: Esporte Total | B20: 89.9 | C20: -0.55 | D20: 75000 | E20: =B20*0.85 -> 76.415 | F20: =D20*(0.85^C20) -> 82012.652 | G20: =E20*F20/1000000 -> 6.2669968 | H20: =B20 -> 89.9 | I20: =D20 -> 75000 | J20: =B20*D20/1000000 -> 6.7425 | K20: =B20*1.15 -> 103.385 | L20: =D20*(1.15^C20) -> 69450.832 | M20: =K20*L20/1000000 -> 7.1801742 | N20: =_xlfn.IFS(M20>J20*1.02,"Aumentar",G20>J20*1.02,"Reduzir",TRUE(),"Manter") -> Aumentar
A21: Futebol Add | B21: 39.9 | C21: -0.48 | D21: 42000 | E21: =B21*0.85 -> 33.915 | F21: =D21*(0.85^C21) -> 45407.564 | G21: =E21*F21/1000000 -> 1.5399975 | H21: =B21 -> 39.9 | I21: =D21 -> 42000 | J21: =B21*D21/1000000 -> 1.6758 | K21: =B21*1.15 -> 45.885 | L21: =D21*(1.15^C21) -> 39274.831 | M21: =K21*L21/1000000 -> 1.8021256 | N21: =_xlfn.IFS(M21>J21*1.02,"Aumentar",G21>J21*1.02,"Reduzir",TRUE(),"Manter") -> Aumentar
A22: TOTAL | G22: =SUM(G16:G21) -> 54.458692 | J22: =SUM(J16:J21) -> 57.072 | M22: =K22*L22/1000000 -> 0 | N22: =_xlfn.IFS(M22>J22*1.02,"Aumentar",G22>J22*1.02,"Reduzir",TRUE(),"Manter") -> Manter

Sheet Pricing_Simulator
A1: PRICING SIMULATOR — PAINEL INTERATIVO DE IMPACTO DE PREÇO
A2: Altere as células AZUIS (Novo Preço Proposto) e veja impacto em assinantes, receita mensal e anualizada em tempo real.
A4: PAINEL DE CONTROLE
A5: Pacote | B5: Preço Atual (R$) | C5: Assin. Atuais | D5: β OLS (Auto) | E5: IC Low (Pess.) | F5: IC High (Otim.) | G5: NOVO PREÇO PROPOSTO (R$) | H5: Δ Preço % | I5: Δ Demanda % (Central) | J5: Assin. Projetados | K5: Receita Atual (R$) | L5: Nova Receita (R$) | M5: Δ Receita % | N5: Status
A6: Futebol | B6: 89.9 | C6: 95000 | D6: =OLS_Coefficients!C6 -> -0.35879861 | E6: =OLS_Coefficients!I6 -> -0.60928086 | F6: =OLS_Coefficients!J6 -> -0.10831635 | G6: 94.9 | H6: =(G6-B6)/B6 -> 0.055617353 | I6: =D6*H6 -> -0.019955429 | J6: =ROUND(C6*(1+I6),0) -> 93104 | K6: =B6*C6 -> 8540500 | L6: =G6*J6 -> 8835569.6 | M6: =(L6-K6)/K6 -> 0.034549453 | N6: =_xlfn.IFS(H6>0.15,"⚠ Reajuste Alto",M6>0,"✓ Receita ↑",M6<-0.05,"⚠ Receita ↓","TRUE","≈ Neutro") -> ✓ Receita ↑
A7: MMA Combate | B7: 64.9 | C7: 42000 | D7: =OLS_Coefficients!C7 -> -0.53921568 | E7: =OLS_Coefficients!I7 -> -0.80072017 | F7: =OLS_Coefficients!J7 -> -0.2777112 | G7: 69.9 | H7: =(G7-B7)/B7 -> 0.077041602 | I7: =D7*H7 -> -0.04154204 | J7: =ROUND(C7*(1+I7),0) -> 40255 | K7: =B7*C7 -> 2725800 | L7: =G7*J7 -> 2813824.5 | M7: =(L7-K7)/K7 -> 0.032293088 | N7: =_xlfn.IFS(H7>0.15,"⚠ Reajuste Alto",M7>0,"✓ Receita ↑",M7<-0.05,"⚠ Receita ↓","TRUE","≈ Neutro") -> ✓ Receita ↑
A8: Familia | B8: 129.9 | C8: 210000 | D8: =OLS_Coefficients!C8 -> -0.73102198 | E8: =OLS_Coefficients!I8 -> -1.0031154 | F8: =OLS_Coefficients!J8 -> -0.45892857 | G8: 139.9 | H8: =(G8-B8)/B8 -> 0.076982294 | I8: =D8*H8 -> -0.056275749 | J8: =ROUND(C8*(1+I8),0) -> 198182 | K8: =B8*C8 -> 27279000 | L8: =G8*J8 -> 27725662 | M8: =(L8-K8)/K8 -> 0.016373833 | N8: =_xlfn.IFS(H8>0.15,"⚠ Reajuste Alto",M8>0,"✓ Receita ↑",M8<-0.05,"⚠ Receita ↓","TRUE","≈ Neutro") -> ✓ Receita ↑
A9: Series Filmes | B9: 49.9 | C9: 68000 | D9: =OLS_Coefficients!C9 -> -1.35 | E9: =OLS_Coefficients!I9 -> -1.634 | F9: =OLS_Coefficients!J9 -> -1.066 | G9: 54.9 | H9: =(G9-B9)/B9 -> 0.1002004 | I9: =D9*H9 -> -0.13527054 | J9: =ROUND(C9*(1+I9),0) -> 58802 | K9: =B9*C9 -> 3393200 | L9: =G9*J9 -> 3228229.8 | M9: =(L9-K9)/K9 -> -0.048617883 | N9: =_xlfn.IFS(H9>0.15,"⚠ Reajuste Alto",M9>0,"✓ Receita ↑",M9<-0.05,"⚠ Receita ↓","TRUE","≈ Neutro") -> ≈ Neutro
A10: Infantil | B10: 39.9 | C10: 55000 | D10: =OLS_Coefficients!C10 -> -0.72170155 | E10: =OLS_Coefficients!I10 -> -1.0484903 | F10: =OLS_Coefficients!J10 -> -0.39491283 | G10: 44.9 | H10: =(G10-B10)/B10 -> 0.12531328 | I10: =D10*H10 -> -0.090438791 | J10: =ROUND(C10*(1+I10),0) -> 50026 | K10: =B10*C10 -> 2194500 | L10: =G10*J10 -> 2246167.4 | M10: =(L10-K10)/K10 -> 0.023544042 | N10: =_xlfn.IFS(H10>0.15,"⚠ Reajuste Alto",M10>0,"✓ Receita ↑",M10<-0.05,"⚠ Receita ↓","TRUE","≈ Neutro") -> ✓ Receita ↑
A11: Bundle Plus | B11: 179.9 | C11: 95000 | D11: =OLS_Coefficients!C11 -> -0.45615572 | E11: =OLS_Coefficients!I11 -> -0.73949735 | F11: =OLS_Coefficients!J11 -> -0.17281409 | G11: 189.9 | H11: =(G11-B11)/B11 -> 0.055586437 | I11: =D11*H11 -> -0.025356071 | J11: =ROUND(C11*(1+I11),0) -> 92591 | K11: =B11*C11 -> 17090500 | L11: =G11*J11 -> 17583031 | M11: =(L11-K11)/K11 -> 0.028818987 | N11: =_xlfn.IFS(H11>0.15,"⚠ Reajuste Alto",M11>0,"✓ Receita ↑",M11<-0.05,"⚠ Receita ↓","TRUE","≈ Neutro") -> ✓ Receita ↑
A12: TOTAL PORTFÓLIO | C12: =SUM(C6:C11) -> 565000 | J12: =SUM(J6:J11) -> 532960 | K12: =SUM(K6:K11) -> 61223500 | L12: =SUM(L6:L11) -> 62432484 | M12: =(L12-K12)/K12 -> 0.019747058
A14: RESUMO DE IMPACTO
A15: Variação de Receita (R$/mês): | I15: =L12-K12 -> 1208984
A16: Variação de Assinantes: | I16: =J12-C12 -> -32040
A17: Variação % de Receita: | I17: =(L12-K12)/K12 -> 0.019747058
A18: Receita Incremental Anualizada (R$): | I18: =(L12-K12)*12 -> 14507808

Sheet Dashboard
A1: PRISM v2.0 | DASHBOARD EXECUTIVO | PRICING & REVENUE INTELLIGENCE FOR STREAMING MARKETS
A2: Claro tv+ | Todas as métricas linkadas automaticamente das abas de modelo. Atualize os inputs e o dashboard recalcula.
A4: KPIs DE PRICING — IMPACTO DOS REAJUSTES PROPOSTOS
A5: Receita Mensal Atual | E5: Receita com Reajustes Propostos | I5: Ganho Mensal Estimado | M5: Ganho Anualizado
A6: =Pricing_Simulator!K12 -> 61223500 | E6: =Pricing_Simulator!L12 -> 62432484 | I6: =Pricing_Simulator!L12-Pricing_Simulator!K12 -> 1208984 | M6: =(Pricing_Simulator!L12-Pricing_Simulator!K12)*12 -> 14507808
A9: MAPA DE PRICING — ELASTICIDADE, WTP E OPORTUNIDADE POR PACOTE
A10: Pacote | B10: Preço Atual | C10: β OLS (IC Low / High) | D10: Classif. | E10: WTP OPP (R$) | F10: Preço Proposto | G10: Δ Preço % | H10: Assin. Projetados | I10: Receita Atual | J10: Receita Proposta | K10: Δ Receita % | L10: Timing Ótimo | M10: IC Range (Incerteza) | N10: Ação
A11: Futebol | B11: 89.9 | C11: =OLS_Coefficients!C6&" ["&TEXT(OLS_Coefficients!I6,"0.00")&"/"&TEXT(OLS_Coefficients!J6,"0.00")&"]" -> -0.358798607870316 [-0.61/-0.11] | D11: Inelástico Forte | E11: =WTP_Conjoint!J6 -> 96.5 | F11: =Pricing_Simulator!G6 -> 94.9 | G11: =Pricing_Simulator!H6 -> 0.055617353 | H11: =Pricing_Simulator!J6 -> 93104 | I11: =Pricing_Simulator!K6 -> 8540500 | J11: =Pricing_Simulator!L6 -> 8835569.6 | K11: =Pricing_Simulator!M6 -> 0.034549453 | L11: Nov | M11: =OLS_Coefficients!J6-OLS_Coefficients!I6 -> 0.50096451 | N11: =Pricing_Simulator!N6 -> ✓ Receita ↑
A12: MMA Combate | B12: 64.9 | C12: =OLS_Coefficients!C7&" ["&TEXT(OLS_Coefficients!I7,"0.00")&"/"&TEXT(OLS_Coefficients!J7,"0.00")&"]" -> -0.539215682993195 [-0.80/-0.28] | D12: Inelástico Moderado | E12: =WTP_Conjoint!J7 -> 69.5 | F12: =Pricing_Simulator!G7 -> 69.9 | G12: =Pricing_Simulator!H7 -> 0.077041602 | H12: =Pricing_Simulator!J7 -> 40255 | I12: =Pricing_Simulator!K7 -> 2725800 | J12: =Pricing_Simulator!L7 -> 2813824.5 | K12: =Pricing_Simulator!M7 -> 0.032293088 | L12: Nov | M12: =OLS_Coefficients!J7-OLS_Coefficients!I7 -> 0.52300897 | N12: =Pricing_Simulator!N7 -> ✓ Receita ↑
A13: Familia | B13: 129.9 | C13: =OLS_Coefficients!C8&" ["&TEXT(OLS_Coefficients!I8,"0.00")&"/"&TEXT(OLS_Coefficients!J8,"0.00")&"]" -> -0.731021982850656 [-1.00/-0.46] | D13: Inelástico Moderado | E13: =WTP_Conjoint!J8 -> 126.5 | F13: =Pricing_Simulator!G8 -> 139.9 | G13: =Pricing_Simulator!H8 -> 0.076982294 | H13: =Pricing_Simulator!J8 -> 198182 | I13: =Pricing_Simulator!K8 -> 27279000 | J13: =Pricing_Simulator!L8 -> 27725662 | K13: =Pricing_Simulator!M8 -> 0.016373833 | L13: Nov | M13: =OLS_Coefficients!J8-OLS_Coefficients!I8 -> 0.54418683 | N13: =Pricing_Simulator!N8 -> ✓ Receita ↑
A14: Series Filmes | B14: 49.9 | C14: =OLS_Coefficients!C9&" ["&TEXT(OLS_Coefficients!I9,"0.00")&"/"&TEXT(OLS_Coefficients!J9,"0.00")&"]" -> -1.35 [-1.63/-1.07] | D14: Elástico | E14: =WTP_Conjoint!J9 -> 56 | F14: =Pricing_Simulator!G9 -> 54.9 | G14: =Pricing_Simulator!H9 -> 0.1002004 | H14: =Pricing_Simulator!J9 -> 58802 | I14: =Pricing_Simulator!K9 -> 3393200 | J14: =Pricing_Simulator!L9 -> 3228229.8 | K14: =Pricing_Simulator!M9 -> -0.048617883 | L14: Out | M14: =OLS_Coefficients!J9-OLS_Coefficients!I9 -> 0.568 | N14: =Pricing_Simulator!N9 -> ≈ Neutro
A15: Infantil | B15: 39.9 | C15: =OLS_Coefficients!C10&" ["&TEXT(OLS_Coefficients!I10,"0.00")&"/"&TEXT(OLS_Coefficients!J10,"0.00")&"]" -> -0.72170155182422 [-1.05/-0.39] | D15: Inelástico Moderado | E15: =WTP_Conjoint!J10 -> 46.5 | F15: =Pricing_Simulator!G10 -> 44.9 | G15: =Pricing_Simulator!H10 -> 0.12531328 | H15: =Pricing_Simulator!J10 -> 50026 | I15: =Pricing_Simulator!K10 -> 2194500 | J15: =Pricing_Simulator!L10 -> 2246167.4 | K15: =Pricing_Simulator!M10 -> 0.023544042 | L15: Nov | M15: =OLS_Coefficients!J10-OLS_Coefficients!I10 -> 0.65357744 | N15: =Pricing_Simulator!N10 -> ✓ Receita ↑
A16: Bundle Plus | B16: 179.9 | C16: =OLS_Coefficients!C11&" ["&TEXT(OLS_Coefficients!I11,"0.00")&"/"&TEXT(OLS_Coefficients!J11,"0.00")&"]" -> -0.456155717841661 [-0.74/-0.17] | D16: Inelástico Forte | E16: =WTP_Conjoint!J11 -> 173.5 | F16: =Pricing_Simulator!G11 -> 189.9 | G16: =Pricing_Simulator!H11 -> 0.055586437 | H16: =Pricing_Simulator!J11 -> 92591 | I16: =Pricing_Simulator!K11 -> 17090500 | J16: =Pricing_Simulator!L11 -> 17583031 | K16: =Pricing_Simulator!M11 -> 0.028818987 | L16: Dez | M16: =OLS_Coefficients!J11-OLS_Coefficients!I11 -> 0.56668326 | N16: =Pricing_Simulator!N11 -> ✓ Receita ↑
A19: METODOLOGIA: OLS Log-Log | ln(Q)=α+β·ln(P)+γ·S+δ·D | IC 95%=β±1.96×SE(β) | WTP via Van Westendorp | Canibalização via elasticidade cruzada | Timing via índice sazonal | PRISM v2.0
